transipy/__init__.py
transipy/main.py
transipy/trans_helper.py
transipy/utils.py
transipy-1.0.6.dist-info/LICENSE
transipy-1.0.6.dist-info/METADATA
transipy-1.0.6.dist-info/WHEEL
transipy-1.0.6.dist-info/entry_points.txt
transipy-1.0.6.dist-info/top_level.txt
transipy-1.0.6.dist-info/RECORD
