Metadata-Version: 2.2
Name: transipy
Version: 1.0.6
Summary: Transipy is your one-stop solution for lightning-fast and accurate document translation.
Home-page: https://github.com/NeiH4207/transipy
Author: Hien Vu, 
Author-email: hienvq23@gmail.com, 
Keywords: google translate,translation,document translation,language translation
Requires-Python: >=3.8
License-File: LICENSE
Requires-Dist: loguru==0.7.2
Requires-Dist: googletrans==4.0.2
Requires-Dist: pandas
Requires-Dist: bottleneck
Requires-Dist: openpyxl==3.1.2
Requires-Dist: requests==2.31.0
Requires-Dist: h2==3.2.0
Requires-Dist: httpx==0.28.1
Requires-Dist: python-docx
Requires-Dist: pytest
Requires-Dist: tqdm
Dynamic: author
Dynamic: author-email
Dynamic: description
Dynamic: description-content-type
Dynamic: home-page
Dynamic: keywords
Dynamic: requires-dist
Dynamic: requires-python
Dynamic: summary
